slothstock/__init__.py
slothstock/constants.py
slothstock/exceptions.py
slothstock/utils.py
slothstock/indicators/__init__.py
slothstock/indicators/macd.py
slothstock/providers/__init__.py
slothstock/providers/xueqiu.py
slothstock/scripts/__init__.py
slothstock/scripts/common.py
slothstock/scripts/helps.py
slothstock/scripts/parsers.py
slothstock/scripts/sloth_buy.py
slothstock/scripts/sloth_sell.py
tests/indicators/__init__.py
tests/indicators/test_macd.py
tests/providers/__init__.py
tests/providers/test_xueqiu.py
slothstock-0.3.2.dist-info/LICENSE
slothstock-0.3.2.dist-info/METADATA
slothstock-0.3.2.dist-info/WHEEL
slothstock-0.3.2.dist-info/entry_points.txt
slothstock-0.3.2.dist-info/top_level.txt
slothstock-0.3.2.dist-info/RECORD
