Metadata-Version: 2.1
Name: slothstock
Version: 0.3.2
Summary: Stock for Sloth.
Home-page: https://github.com/huxuan/slothstock
Author: Xuan (Sean) Hu
Author-email: i+slothstock@huxuan.org
License: MIT
Keywords: stock
Platform: UNKNOWN
Classifier: Development Status :: 4 - Beta
Classifier: License :: OSI Approved :: MIT License
Classifier: Programming Language :: Python :: 3
Classifier: Programming Language :: Python :: 3 :: Only
Classifier: Topic :: Office/Business :: Financial
Classifier: Topic :: Utilities
Requires-Python: >=3
Requires-Dist: faker
Requires-Dist: pandas
Requires-Dist: requests
Requires-Dist: ta-lib
Requires-Dist: tqdm
Requires-Dist: wxpusher
